Products.MemoryProfiler-configure.zcml
README.txt
setup.cfg
setup.py
Products/__init__.py
Products.MemoryProfiler.egg-info/PKG-INFO
Products.MemoryProfiler.egg-info/SOURCES.txt
Products.MemoryProfiler.egg-info/dependency_links.txt
Products.MemoryProfiler.egg-info/entry_points.txt
Products.MemoryProfiler.egg-info/namespace_packages.txt
Products.MemoryProfiler.egg-info/not-zip-safe
Products.MemoryProfiler.egg-info/requires.txt
Products.MemoryProfiler.egg-info/top_level.txt
Products/MemoryProfiler/LICENSE.txt
Products/MemoryProfiler/MemoryProfiler.py
Products/MemoryProfiler/README.txt
Products/MemoryProfiler/__init__.py
Products/MemoryProfiler/showDocumentation.dtml
Products/MemoryProfiler/tests.py
Products/MemoryProfiler/version.txt
Products/MemoryProfiler/www/memory.html
docs/HISTORY.txt