Metadata-Version: 1.0
Name: Products.MemoryProfiler
Version: 0.1
Summary: A memory profiler for zope
Home-page: https://svn.plone.org/svn/collective/Products.MemoryProfiler/
Author: Youenn Boussard [ingeniweb]
Author-email: y.boussard@ingeniweb.com
License: GPL
Keywords: Memory Profiler Zope
Platform: UNKNOWN
Classifier: Programming Language :: Python
Classifier: Framework :: Zope2
Classifier: Topic :: System :: Monitoring
Classifier: Topic :: Utilities
Classifier: Topic :: Software Development :: Libraries :: Python Modules
